rcute_ai/__init__.py
rcute_ai/_speech_detector_picovoice.py
rcute_ai/_speech_detector_snowboy.py
rcute_ai/face_recognizer.py
rcute_ai/hotword_recognizer_pocketsphinx.py
rcute_ai/hotword_recognizer_snowboy.py
rcute_ai/object_recognizer.py
rcute_ai/qrcode_recognizer.py
rcute_ai/stt_vosk.py
rcute_ai/tts_espeak.py
rcute_ai/tts_pyttsx3.py
rcute_ai/util.py
rcute_ai/version.py
rcute_ai/wake_word_detector_vosk.py
rcute_ai-0.1.1.dist-info/DESCRIPTION.rst
rcute_ai-0.1.1.dist-info/METADATA
rcute_ai-0.1.1.dist-info/RECORD
rcute_ai-0.1.1.dist-info/WHEEL
rcute_ai-0.1.1.dist-info/metadata.json
rcute_ai-0.1.1.dist-info/top_level.txt
