Metadata-Version: 2.0
Name: rcute-ai
Version: 0.1.1
Summary: Simple wrapper over some python libs for image/audio detection/recognition etc
Home-page: https://github.com/r-cute/rcute-ai
Author: Huang Yan
Author-email: hyansuper@foxmail.com
License: MIT
Platform: UNKNOWN
Classifier: Programming Language :: Python :: 3.7
Classifier: License :: OSI Approved :: MIT License
Classifier: Operating System :: OS Independent
Requires-Dist: Pillow
Requires-Dist: face-recognition
Requires-Dist: numpy
Requires-Dist: opencv-contrib-python
Requires-Dist: opencv-python
Requires-Dist: pydub
Requires-Dist: pyttsx3
Requires-Dist: vosk
